setup.py
matmodlab/__init__.py
matmodlab/constants.py
matmodlab/mml_siteenv.py
matmodlab/product.py
matmodlab.egg-info/PKG-INFO
matmodlab.egg-info/SOURCES.txt
matmodlab.egg-info/dependency_links.txt
matmodlab.egg-info/not-zip-safe
matmodlab.egg-info/requires.txt
matmodlab.egg-info/top_level.txt
matmodlab/bin/fdiff
matmodlab/bin/fdump
matmodlab/bin/mmd
matmodlab/bin/mml
matmodlab/bin/mml-osx
matmodlab/examples/Hyperfit.ipynb
matmodlab/examples/MasterCurve.ipynb
matmodlab/examples/Materials.ipynb
matmodlab/examples/MooneyRivlin.ipynb
matmodlab/examples/Optimization.ipynb
matmodlab/examples/Permutation.ipynb
matmodlab/examples/TargetStress.ipynb
matmodlab/examples/Treloar_hyperelastic_data.xlsx
matmodlab/examples/UniaxialStress.ipynb
matmodlab/examples/__init__.py
matmodlab/examples/data_steps.py
matmodlab/examples/expansion.py
matmodlab/examples/gen_steps.py
matmodlab/examples/hello_world.ipynb
matmodlab/examples/hello_world.py
matmodlab/examples/linear_elastic.py
matmodlab/examples/mat_user.py
matmodlab/examples/mcgen.csv
matmodlab/examples/mimic.py
matmodlab/examples/mml_userenv.py
matmodlab/examples/mooney_rivlin.py
matmodlab/examples/multi_step.py
matmodlab/examples/optimize.py
matmodlab/examples/optimize.xls
matmodlab/examples/permutate.py
matmodlab/examples/plastic.py
matmodlab/examples/polyhyper.py
matmodlab/examples/show
matmodlab/examples/uanisohyper_inv.py
matmodlab/examples/uhyper.py
matmodlab/examples/umat.f
matmodlab/examples/umat.py
matmodlab/examples/uniaxial_strain.py
matmodlab/examples/uniaxial_stress.py
matmodlab/examples/user.py
matmodlab/examples/user_std.py
matmodlab/examples/viscoelastic.py
matmodlab/fitting/__init__.py
matmodlab/fitting/hyperopt.py
matmodlab/fitting/mcgen.py
matmodlab/ipynb/custom/custom.css
matmodlab/ipynb/custom/custom.js
matmodlab/ipynb/profile_default/db/.file
matmodlab/ipynb/profile_default/startup/matmodlab.ipy
matmodlab/ipynb/profile_default/static/custom/custom.css
matmodlab/ipynb/profile_default/static/custom/custom.js
matmodlab/lib/__init__.py
matmodlab/materials/__init__.py
matmodlab/materials/addon_expansion.py
matmodlab/materials/addon_expansion_f.py
matmodlab/materials/addon_trs.py
